manuelharofulgencio3/__init__.py
manuelharofulgencio3/opengate_client.py
manuelharofulgencio3/ai_models/__init__.py
manuelharofulgencio3/ai_models/ai_models.py
manuelharofulgencio3/ai_pipelines/__init__.py
manuelharofulgencio3/ai_pipelines/ai_pipelines.py
manuelharofulgencio3/ai_transformers/__init__.py
manuelharofulgencio3/ai_transformers/ai_transformers.py
manuelharofulgencio3/datapoints/__init__.py
manuelharofulgencio3/datapoints/datapoints.py
manuelharofulgencio3/datasets/__init__.py
manuelharofulgencio3/datasets/datasets.py
manuelharofulgencio3/entities/__init__.py
manuelharofulgencio3/entities/entities.py
manuelharofulgencio3/rules/__init__.py
manuelharofulgencio3/rules/rules.py
manuelharofulgencio3/test/__init__.py
manuelharofulgencio3/test/ownworld.py
manuelharofulgencio3/test/test_steps_cucumber.py
manuelharofulgencio3/timeseries/__init__.py
manuelharofulgencio3/timeseries/timeseries.py
manuelharofulgencio3-1.0.0.dist-info/METADATA
manuelharofulgencio3-1.0.0.dist-info/WHEEL
manuelharofulgencio3-1.0.0.dist-info/top_level.txt
manuelharofulgencio3-1.0.0.dist-info/RECORD
