Metadata-Version: 2.1
Name: manuelharofulgencio3
Version: 1.0.0
Summary: description
Author: manuel
Author-email: manuel.haro@amplia.es
License: Apache License 2.0
Requires-Dist: pandas
Requires-Dist: requests
Requires-Dist: jsonpath-ng
Requires-Dist: numpy
Requires-Dist: urllib3
Requires-Dist: configparser
Requires-Dist: parse
